adafruit_74hc595.py
adafruit_circuitpython_74hc595-1.5.0.dist-info/licenses/LICENSE
adafruit_circuitpython_74hc595-1.5.0.dist-info/METADATA
adafruit_circuitpython_74hc595-1.5.0.dist-info/WHEEL
adafruit_circuitpython_74hc595-1.5.0.dist-info/top_level.txt
adafruit_circuitpython_74hc595-1.5.0.dist-info/RECORD
